peek/__init__.py
peek/ann_structure.py
peek/metrics.py
peek/rwsl.py
peek/stats.py
peek/txt.py
brat_peek-0.1.2.dist-info/METADATA
brat_peek-0.1.2.dist-info/WHEEL
brat_peek-0.1.2.dist-info/top_level.txt
brat_peek-0.1.2.dist-info/RECORD
