Metadata-Version: 2.4
Name: brat-peek
Version: 0.1.2
Summary: Simple utilities to read/write brat standoff files (peek module)
Home-page: https://github.com/s-lilo/brat-peek
Author: Salvador Lima López
License: MIT
Classifier: Programming Language :: Python :: 3
Classifier: License :: OSI Approved :: MIT License
Classifier: Operating System :: OS Independent
Dynamic: author
Dynamic: classifier
Dynamic: description
Dynamic: description-content-type
Dynamic: home-page
Dynamic: license
Dynamic: summary
